labelImg/__init__.py
labelImg/labelImg.py
libs/__init__.py
libs/canvas.py
libs/colorDialog.py
libs/constants.py
libs/hashableQListWidgetItem.py
libs/labelDialog.py
libs/labelFile.py
libs/pascal_voc_io.py
libs/resources.py
libs/settings.py
libs/shape.py
libs/stringBundle.py
libs/toolBar.py
libs/ustr.py
libs/utils.py
libs/yolo_io.py
libs/zoomWidget.py
labelImg-1.8.3.dist-info/LICENSE
labelImg-1.8.3.dist-info/METADATA
labelImg-1.8.3.dist-info/WHEEL
labelImg-1.8.3.dist-info/entry_points.txt
labelImg-1.8.3.dist-info/top_level.txt
labelImg-1.8.3.dist-info/RECORD
